Etape/__init__.py
Etape/_version.py
Etape/data/all.dev.lst
Etape/data/all.dev.uem
Etape/data/all.trn.lst
Etape/data/all.trn.uem
Etape/data/all.tst.lst
Etape/data/all.tst.mdtm
Etape/data/all.tst.uem
Etape/data/debug.dev.lst
Etape/data/debug.dev.mdtm
Etape/data/debug.dev.uem
Etape/data/debug.trn.lst
Etape/data/debug.trn.mdtm
Etape/data/debug.trn.uem
Etape/data/debug.tst.lst
Etape/data/debug.tst.mdtm
Etape/data/debug.tst.uem
Etape/data/radio.dev.lst
Etape/data/radio.dev.uem
Etape/data/radio.trn.lst
Etape/data/radio.trn.uem
Etape/data/radio.tst.lst
Etape/data/radio.tst.mdtm
Etape/data/radio.tst.uem
Etape/data/tv.dev.lst
Etape/data/tv.dev.mdtm
Etape/data/tv.dev.uem
Etape/data/tv.trn.lst
Etape/data/tv.trn.mdtm
Etape/data/tv.trn.uem
Etape/data/tv.tst.lst
Etape/data/tv.tst.mdtm
Etape/data/tv.tst.uem
pyannote.db.etape-0.4.dist-info/DESCRIPTION.rst
pyannote.db.etape-0.4.dist-info/entry_points.txt
pyannote.db.etape-0.4.dist-info/METADATA
pyannote.db.etape-0.4.dist-info/metadata.json
pyannote.db.etape-0.4.dist-info/RECORD
pyannote.db.etape-0.4.dist-info/top_level.txt
pyannote.db.etape-0.4.dist-info/WHEEL
